netmax/__init__.py
netmax/agent.py
netmax/influence_maximization.py
netmax/algorithms/__init__.py
netmax/algorithms/algorithm.py
netmax/algorithms/proxy_based/__init__.py
netmax/algorithms/proxy_based/degdis.py
netmax/algorithms/proxy_based/group_pr.py
netmax/algorithms/proxy_based/highest_out_degree.py
netmax/algorithms/proxy_based/proxy_based.py
netmax/algorithms/simulation_based/__init__.py
netmax/algorithms/simulation_based/celf.py
netmax/algorithms/simulation_based/celfpp.py
netmax/algorithms/simulation_based/mcgreedy.py
netmax/algorithms/simulation_based/simulation_based.py
netmax/algorithms/sketch_based/__init__.py
netmax/algorithms/sketch_based/ris.py
netmax/algorithms/sketch_based/sketch_based.py
netmax/algorithms/sketch_based/static_greedy.py
netmax/algorithms/sketch_based/tim.py
netmax/algorithms/sketch_based/timp.py
netmax/diffusion_models/__init__.py
netmax/diffusion_models/decreasing_cascade.py
netmax/diffusion_models/diffusion_model.py
netmax/diffusion_models/independent_cascade.py
netmax/diffusion_models/linear_threshold.py
netmax/diffusion_models/np_f2dlt.py
netmax/diffusion_models/sp_f2dlt.py
netmax/diffusion_models/triggering.py
netmax/endorsement_policies/__init__.py
netmax/endorsement_policies/community.py
netmax/endorsement_policies/endorsement_policy.py
netmax/endorsement_policies/random.py
netmax/endorsement_policies/similarity.py
netmax/endorsement_policies/voting.py
netmax/influence_probabilities/__init__.py
netmax/influence_probabilities/constant.py
netmax/influence_probabilities/hybrid.py
netmax/influence_probabilities/influence_probability.py
netmax/influence_probabilities/opinion_based.py
netmax/influence_probabilities/ratio_model.py
netmax/influence_probabilities/similarity.py
netmax/influence_probabilities/uniform.py
netmax-1.0.0.dist-info/LICENSE.txt
netmax-1.0.0.dist-info/METADATA
netmax-1.0.0.dist-info/WHEEL
netmax-1.0.0.dist-info/top_level.txt
netmax-1.0.0.dist-info/RECORD
