Metadata-Version: 2.1
Name: netmax
Version: 1.0.0
Summary: Library for the problem of Influence Maximization in Social Networks
Author-email: Lorenzo Bloise <l.bloise@outlook.it>, Carmelo Gugliotta <carmelo.gugliotta00@gmail.com>
Project-URL: Homepage, https://github.com/lorenzobloise/netmax
Project-URL: Issues, https://github.com/lorenzobloise/netmax/issues
Keywords: influence-maximization,network-analysis,simulator,complex-networks
Classifier: Programming Language :: Python :: 3
Classifier: License :: OSI Approved :: MIT License
Classifier: Operating System :: OS Independent
Classifier: Development Status :: 5 - Production/Stable
Classifier: Intended Audience :: Science/Research
Classifier: Topic :: Scientific/Engineering :: Information Analysis
Requires-Python: >=3.10
License-File: LICENSE.txt
Requires-Dist: networkx==3.3
Requires-Dist: numpy
Requires-Dist: scipy
Requires-Dist: tqdm
Requires-Dist: heapdict
